sjrpc2/__init__.py
sjrpc2/cli.py
sjrpc2/sjrpc2.py
sjrpc2-0.1.0.dist-info/AUTHORS.rst
sjrpc2-0.1.0.dist-info/LICENSE
sjrpc2-0.1.0.dist-info/METADATA
sjrpc2-0.1.0.dist-info/WHEEL
sjrpc2-0.1.0.dist-info/entry_points.txt
sjrpc2-0.1.0.dist-info/top_level.txt
sjrpc2-0.1.0.dist-info/RECORD
